searchlight_ui/__init__.py
searchlight_ui/karma.conf.js
searchlight_ui/test-shim.js
searchlight_ui/version.py
searchlight_ui/api/__init__.py
searchlight_ui/api/rest/__init__.py
searchlight_ui/api/rest/searchlight.py
searchlight_ui/conf/README.rst
searchlight_ui/conf/searchlight_policy.json
searchlight_ui/dashboards/__init__.py
searchlight_ui/dashboards/project/__init__.py
searchlight_ui/dashboards/project/search/__init__.py
searchlight_ui/dashboards/project/search/panel.py
searchlight_ui/dashboards/project/search/urls.py
searchlight_ui/dashboards/project/search/views.py
searchlight_ui/enabled/_1001_project_search_panel.py
searchlight_ui/enabled/__init__.py
searchlight_ui/local_settings.d/_1001_search_settings.py
searchlight_ui/locale/ca/LC_MESSAGES/django.po
searchlight_ui/locale/cs/LC_MESSAGES/django.po
searchlight_ui/locale/cs/LC_MESSAGES/djangojs.po
searchlight_ui/locale/de/LC_MESSAGES/django.po
searchlight_ui/locale/de/LC_MESSAGES/djangojs.po
searchlight_ui/locale/en_AU/LC_MESSAGES/django.po
searchlight_ui/locale/en_GB/LC_MESSAGES/django.po
searchlight_ui/locale/en_GB/LC_MESSAGES/djangojs.po
searchlight_ui/locale/es/LC_MESSAGES/django.po
searchlight_ui/locale/fr/LC_MESSAGES/django.po
searchlight_ui/locale/fr/LC_MESSAGES/djangojs.po
searchlight_ui/locale/id/LC_MESSAGES/django.po
searchlight_ui/locale/id/LC_MESSAGES/djangojs.po
searchlight_ui/locale/it/LC_MESSAGES/django.po
searchlight_ui/locale/ja/LC_MESSAGES/django.po
searchlight_ui/locale/ja/LC_MESSAGES/djangojs.po
searchlight_ui/locale/ko_KR/LC_MESSAGES/django.po
searchlight_ui/locale/ko_KR/LC_MESSAGES/djangojs.po
searchlight_ui/locale/pt/LC_MESSAGES/django.po
searchlight_ui/locale/pt_BR/LC_MESSAGES/django.po
searchlight_ui/locale/ru/LC_MESSAGES/django.po
searchlight_ui/locale/ru/LC_MESSAGES/djangojs.po
searchlight_ui/locale/tr_TR/LC_MESSAGES/django.po
searchlight_ui/locale/tr_TR/LC_MESSAGES/djangojs.po
searchlight_ui/locale/zh_CN/LC_MESSAGES/django.po
searchlight_ui-9.0.0.dist-info/DESCRIPTION.rst
searchlight_ui-9.0.0.dist-info/METADATA
searchlight_ui-9.0.0.dist-info/RECORD
searchlight_ui-9.0.0.dist-info/WHEEL
searchlight_ui-9.0.0.dist-info/metadata.json
searchlight_ui-9.0.0.dist-info/pbr.json
searchlight_ui-9.0.0.dist-info/top_level.txt
