Metadata-Version: 2.0
Name: searchlight-ui
Version: 9.0.0
Summary: Horizon panels and libraries for Searchlight
Home-page: https://docs.openstack.org/searchlight/latest
Author: OpenStack
Author-email: openstack-discuss@lists.openstack.org
License: UNKNOWN
Platform: UNKNOWN
Classifier: Environment :: OpenStack
Classifier: Intended Audience :: Information Technology
Classifier: Intended Audience :: System Administrators
Classifier: License :: OSI Approved :: Apache Software License
Classifier: Operating System :: POSIX :: Linux
Classifier: Programming Language :: Python
Classifier: Programming Language :: Python :: 3
Classifier: Programming Language :: Python :: 3.6
Classifier: Programming Language :: Python :: 3.7
Classifier: Programming Language :: Python :: 3.8
Classifier: Programming Language :: Python :: 3 :: Only
Requires-Python: >=3.6
Requires-Dist: Babel (>=1.3)
Requires-Dist: horizon (>=17.1.0)
Requires-Dist: oslo.log (>=3.36.0)
Requires-Dist: pbr (!=2.1.0,>=2.0.0)
